hexlet/pairs/__init__.py
hexlet_pairs-0.1.2.dist-info/LICENSE
hexlet_pairs-0.1.2.dist-info/WHEEL
hexlet_pairs-0.1.2.dist-info/METADATA
hexlet_pairs-0.1.2.dist-info/RECORD
